__init__.py
config.py
main.py
api/__init__.py
api/admin.py
api/bot.py
api/handlers.py
api/help.py
api/menu.py
api/menu_utils.py
api/reports.py
api/sandbox.py
api/security.py
api/settings.py
api/telegram.py
api/threat_intelligence.py
api/users.py
api/remote/__init__.py
api/remote/sb_analysis.py
api/remote/sb_history.py
api/remote/sb_reports.py
api/remote/sb_task_info.py
api/remote/sb_user.py
db/__init__.py
db/api_keys.py
db/common.py
db/director.py
db/users.py
lang/__init__.py
lang/context.py
lang/director.py
utils/__init__.py
utils/director.py
utils/logger.py
anyrun_tg_bot-0.6.4.dist-info/METADATA
anyrun_tg_bot-0.6.4.dist-info/WHEEL
anyrun_tg_bot-0.6.4.dist-info/entry_points.txt
anyrun_tg_bot-0.6.4.dist-info/top_level.txt
anyrun_tg_bot-0.6.4.dist-info/RECORD
