Metadata-Version: 2.1
Name: anyrun-tg-bot
Version: 0.6.4
Summary: A Telegram bot for interacting with the ANY.RUN API
Author-email: Kirill Bykov <me@bykovk.pro>
License: MIT License
Project-URL: Homepage, https://any.run
Project-URL: Repository, https://github.com/bykovk-pro/ANY.RUN-for-Telegram
Keywords: anyrun,any.run,telegram,bot,api,malware,analysis,security,sandbox,threat intelligence,cybersecurity
Classifier: Development Status :: 3 - Alpha
Classifier: Intended Audience :: Customer Service
Classifier: Intended Audience :: Education
Classifier: Intended Audience :: Information Technology
Classifier: Intended Audience :: Science/Research
Classifier: Topic :: Security
Classifier: Topic :: Education
Classifier: Topic :: Utilities
Classifier: License :: OSI Approved :: MIT License
Classifier: Programming Language :: Python :: 3.10
Classifier: Operating System :: MacOS
Classifier: Operating System :: POSIX :: Linux
Classifier: Operating System :: Microsoft :: Windows
Requires-Python: >=3.10
Requires-Dist: python-telegram-bot==21.6
Requires-Dist: python-dotenv==1.0.1
Requires-Dist: requests==2.32.3
Requires-Dist: aiosqlite==0.20.0
Requires-Dist: pyzipper==0.3.6
Requires-Dist: watchdog==2.2.1
Requires-Dist: aiohttp==3.10.10
Requires-Dist: validators==0.34.0
Requires-Dist: psutil==6.0.0
Requires-Dist: pyinstaller==6.1.0
Requires-Dist: pyinstaller-hooks-contrib==2024.8
Requires-Dist: python-daemon==3.0.1
Requires-Dist: python-dateutil==2.8.2
